awsrun/__init__.py
awsrun/acctload.py
awsrun/argparse.py
awsrun/cache.py
awsrun/cli.py
awsrun/cloudwatch.py
awsrun/cmdmgr.py
awsrun/config.py
awsrun/plugmgr.py
awsrun/runner.py
awsrun/commands/__init__.py
awsrun/commands/aws/__init__.py
awsrun/commands/aws/access_report.py
awsrun/commands/aws/aws.py
awsrun/commands/aws/cidr_overlap.py
awsrun/commands/aws/console.py
awsrun/commands/aws/dx_maint.py
awsrun/commands/aws/dx_status.py
awsrun/commands/aws/kubectl.py
awsrun/commands/aws/last.py
awsrun/commands/aws/list_hosted_zones.py
awsrun/commands/aws/list_iam_policies.py
awsrun/commands/aws/list_iam_roles.py
awsrun/commands/aws/list_igws.py
awsrun/commands/aws/list_lambdas.py
awsrun/commands/aws/list_public_ips.py
awsrun/commands/aws/list_vpc_attribute.py
awsrun/commands/aws/list_vpcs.py
awsrun/commands/azure/__init__.py
awsrun/commands/azure/az.py
awsrun/commands/azure/cidr_overlap.py
awsrun/commands/azure/list_udrs.py
awsrun/commands/azure/list_vnets.py
awsrun/plugins/__init__.py
awsrun/plugins/accts/__init__.py
awsrun/plugins/accts/azure.py
awsrun/plugins/creds/__init__.py
awsrun/plugins/creds/aws.py
awsrun/plugins/creds/azure.py
awsrun/session/__init__.py
awsrun/session/aws.py
awsrun/session/azure.py
awsrun-3.2.1.dist-info/LICENSE.md
awsrun-3.2.1.dist-info/METADATA
awsrun-3.2.1.dist-info/WHEEL
awsrun-3.2.1.dist-info/entry_points.txt
awsrun-3.2.1.dist-info/top_level.txt
awsrun-3.2.1.dist-info/RECORD
