Metadata-Version: 2.1
Name: awsrun
Version: 3.2.1
Summary: CLI and library to execute commands over one or more AWS or Azure accounts concurrently.
Author-email: Pete Kazmier <opensource@fidelity.com>
Project-URL: homepage, https://github.com/fidelity/awsrun
Keywords: aws,azure,cli,command runner
Classifier: Development Status :: 5 - Production/Stable
Classifier: Intended Audience :: Developers
Classifier: Intended Audience :: System Administrators
Classifier: License :: OSI Approved :: Apache Software License
Classifier: Operating System :: Unix
Classifier: Operating System :: POSIX
Classifier: Operating System :: Microsoft :: Windows
Classifier: Programming Language :: Python
Classifier: Programming Language :: Python :: 3
Classifier: Programming Language :: Python :: 3.7
Classifier: Programming Language :: Python :: 3.8
Classifier: Programming Language :: Python :: 3.9
Classifier: Programming Language :: Python :: 3.10
Classifier: Programming Language :: Python :: 3.11
Classifier: Programming Language :: Python :: Implementation :: CPython
Classifier: Topic :: Utilities
Requires-Python: >=3.7
License-File: LICENSE.md
Requires-Dist: PyYAML>=3.10
Requires-Dist: requests
Requires-Dist: requests_file
Requires-Dist: requests_ntlm
Provides-Extra: all
Requires-Dist: awsrun[aws,azure,cmds,dev]; extra == "all"
Provides-Extra: aws
Requires-Dist: boto3>=1.12.39; extra == "aws"
Requires-Dist: bs4; extra == "aws"
Provides-Extra: azure
Requires-Dist: azure-identity; extra == "azure"
Requires-Dist: azure-mgmt-network; extra == "azure"
Provides-Extra: cmds
Requires-Dist: awsrun[dx-maint,dx-status,last]; extra == "cmds"
Provides-Extra: last
Requires-Dist: pyperclip; extra == "last"
Requires-Dist: colorama; extra == "last"
Requires-Dist: rich; extra == "last"
Requires-Dist: textual==0.20; extra == "last"
Provides-Extra: dx-maint
Requires-Dist: colorama; extra == "dx-maint"
Provides-Extra: dx-status
Requires-Dist: colorama; extra == "dx-status"
Requires-Dist: asciichartpy>=1.5.25; extra == "dx-status"
Requires-Dist: pysparklines>=1.0; extra == "dx-status"
Provides-Extra: dev
Requires-Dist: black; extra == "dev"
Requires-Dist: flake8; extra == "dev"
Requires-Dist: freezegun; extra == "dev"
Requires-Dist: isort; extra == "dev"
Requires-Dist: pdoc3; extra == "dev"
Requires-Dist: pytest; extra == "dev"
Requires-Dist: pytest-mock; extra == "dev"
